setup.py
reddaj_distributions/Binomialdistribution.py
reddaj_distributions/Gaussiandistribution.py
reddaj_distributions/Generaldistribution.py
reddaj_distributions/__init__.py
reddaj_distributions.egg-info/PKG-INFO
reddaj_distributions.egg-info/SOURCES.txt
reddaj_distributions.egg-info/dependency_links.txt
reddaj_distributions.egg-info/not-zip-safe
reddaj_distributions.egg-info/top_level.txt