Metadata-Version: 1.0
Name: reddaj-distributions
Version: 0.1
Summary: Gaussian distributions and Binomial distributions
Home-page: UNKNOWN
Author: Jadder Moya
Author-email: jadder.moya@gmail.com
License: UNKNOWN
Platform: UNKNOWN
